{
  "name": "lightdash-mcp-server",
  "description": "A MCP(Model Context Protocol) server that accesses to Lightdash. This server provides MCP-compatible access to Lightdash's API, allowing AI assistants to interact with your Lightdash data through a standardized interface.",
  "mcpversion": "1.0",
  "serverversion": "0.0.1",
  "repository": {
    "url": "https://github.com/syucream/lightdash-mcp-server",
    "name": "syucream/lightdash-mcp-server"
  },
  "tools": [
    {
      "name": "lightdash_list_projects",
      "description": "List all projects in the Lightdash organization",
      "inputschema": {
        "type": "object"
      }
    },
    {
      "name": "lightdash_get_project",
      "description": "Get details of a specific project",
      "inputschema": {
        "type": "object"
      }
    },
    {
      "name": "lightdash_list_spaces",
      "description": "List all spaces in a project",
      "inputschema": {
        "type": "object"
      }
    },
    {
      "name": "lightdash_list_charts",
      "description": "List all charts in a project",
      "inputschema": {
        "type": "object"
      }
    },
    {
      "name": "lightdash_list_dashboards",
      "description": "List all dashboards in a project",
      "inputschema": {
        "type": "object"
      }
    },
    {
      "name": "lightdash_get_custom_metrics",
      "description": "Get custom metrics for a project",
      "inputschema": {
        "type": "object"
      }
    },
    {
      "name": "lightdash_get_catalog",
      "description": "Get catalog for a project",
      "inputschema": {
        "type": "object"
      }
    },
    {
      "name": "lightdash_get_metrics_catalog",
      "description": "Get metrics catalog for a project",
      "inputschema": {
        "type": "object"
      }
    },
    {
      "name": "lightdash_get_charts_as_code",
      "description": "Get charts as code for a project",
      "inputschema": {
        "type": "object"
      }
    },
    {
      "name": "lightdash_get_dashboards_as_code",
      "description": "Get dashboards as code for a project",
      "inputschema": {
        "type": "object"
      }
    },
    {
      "name": "lightdash_get_metadata",
      "description": "Get metadata for a specific table in the data catalog",
      "inputschema": {
        "type": "object"
      }
    },
    {
      "name": "lightdash_get_analytics",
      "description": "Get analytics for a specific table in the data catalog",
      "inputschema": {
        "type": "object"
      }
    },
    {
      "name": "lightdash_get_user_attributes",
      "description": "Get organization user attributes",
      "inputschema": {
        "type": "object"
      }
    }
  ],
  "endpoints": {
    "stdio": {
      "deployment": "sandbox"
    }
  },
  "deployment": {
    "sandbox": {
      "runtime": "node",
      "package": "lightdash-mcp-server",
      "command": "npx",
      "args": [
        "-y",
        "lightdash-mcp-server"
      ],
      "env": [
        {
          "name": "LIGHTDASH_API_KEY",
          "description": "Your Lightdash PAT",
          "required": true
        },
        {
          "name": "LIGHTDASH_API_URL",
          "description": "The API base URL",
          "required": true
        }
      ]
    }
  }
}